formally/__init__.py
formally/example.py
formally-0.0.1.dist-info/LICENSE
formally-0.0.1.dist-info/METADATA
formally-0.0.1.dist-info/WHEEL
formally-0.0.1.dist-info/top_level.txt
formally-0.0.1.dist-info/RECORD
