Metadata-Version: 2.1
Name: formally
Version: 0.0.1
Summary: Formally - Create quick html forms with python
Home-page: https://github.com/xzava/formally
Author: Mike Hall
Author-email: micheal.hall+formally@gmail.com
License: UNKNOWN
Project-URL: Bug Tracker, https://github.com/xzava/formally/issues
Platform: UNKNOWN
Classifier: Programming Language :: Python :: 3
Classifier: License :: OSI Approved :: MIT License
Classifier: Operating System :: OS Independent
Requires-Python: >=3.6
License-File: LICENSE
